odoo9_addon_admin_technical_features-9.0.0.1.0-py2.7-nspkg.pth
odoo_addons/admin_technical_features/res_groups.xml
odoo_addons/admin_technical_features/__openerp__.py
odoo_addons/admin_technical_features/__init__.py
odoo_addons/admin_technical_features/README.rst
odoo_addons/admin_technical_features/static/admin_technical_features.png
odoo_addons/admin_technical_features/static/description/icon.png
odoo9_addon_admin_technical_features-9.0.0.1.0.dist-info/top_level.txt
odoo9_addon_admin_technical_features-9.0.0.1.0.dist-info/WHEEL
odoo9_addon_admin_technical_features-9.0.0.1.0.dist-info/RECORD
odoo9_addon_admin_technical_features-9.0.0.1.0.dist-info/metadata.json
odoo9_addon_admin_technical_features-9.0.0.1.0.dist-info/DESCRIPTION.rst
odoo9_addon_admin_technical_features-9.0.0.1.0.dist-info/METADATA
odoo9_addon_admin_technical_features-9.0.0.1.0.dist-info/namespace_packages.txt
